inmetpy/__init__.py
inmetpy/exceptions.py
inmetpy/stations.py
inmetpy-0.2.1.data/scripts/inmetpy
tests/__init__.py
tests/test_stations.py
inmetpy-0.2.1.dist-info/METADATA
inmetpy-0.2.1.dist-info/WHEEL
inmetpy-0.2.1.dist-info/top_level.txt
inmetpy-0.2.1.dist-info/RECORD
