Metadata-Version: 2.1
Name: inmetpy
Version: 0.2.1
Summary: A Python API Client to consume the API of the Brazilian National Institute of Meteorology - INMET
Home-page: https://github.com/ocfgaldino/inmetpy
Author: Felippe Galdino, Tobias Ferreira
Author-email: ocfgaldino@gmail.com
License: GPLv3+
Requires-Dist: certifi (==2022.6.15)
Requires-Dist: charset-normalizer (==2.1.0)
Requires-Dist: idna (==3.3)
Requires-Dist: numpy (==1.23.2)
Requires-Dist: pandas (==1.4.3)
Requires-Dist: python-dateutil (==2.8.2)
Requires-Dist: pytz (==2022.2.1)
Requires-Dist: requests (==2.28.1)
Requires-Dist: six (==1.16.0)
Requires-Dist: urllib3 (==1.26.11)
Requires-Dist: yaspin (==2.2.0)
